gen0_ai_helpers/__init__.py
gen0_ai_helpers/core.py
gen0_ai_helpers/utils.py
gen0_ai_helpers-0.1.0.dist-info/licenses/LICENSE
gen0_ai_helpers-0.1.0.dist-info/METADATA
gen0_ai_helpers-0.1.0.dist-info/WHEEL
gen0_ai_helpers-0.1.0.dist-info/top_level.txt
gen0_ai_helpers-0.1.0.dist-info/RECORD
