Metadata-Version: 2.4
Name: gen0_ai_helpers
Version: 0.1.0
Summary: AI helper library using Gemini REST API for text generation.
Author-email: Dion Siji <dionsijik@gmail.com>
License: MIT License
Requires-Python: >=3.8
License-File: LICENSE
Requires-Dist: requests
Dynamic: license-file
